CHANGELOG.md
openapi_tester/__init__.py
openapi_tester/case_testers.py
openapi_tester/clients.py
openapi_tester/constants.py
openapi_tester/exceptions.py
openapi_tester/loaders.py
openapi_tester/py.typed
openapi_tester/schema_tester.py
openapi_tester/utils.py
openapi_tester/validators.py
django_contract_tester-3.3.9.dist-info/LICENSE
django_contract_tester-3.3.9.dist-info/METADATA
django_contract_tester-3.3.9.dist-info/WHEEL
django_contract_tester-3.3.9.dist-info/RECORD
