Metadata-Version: 2.1
Name: django-contract-tester
Version: 3.3.9
Summary: Test utility for validating OpenAPI response documentation
Home-page: https://github.com/maticardenas/django-contract-tester
License: BSD-4-Clause
Keywords: openapi,swagger,api,testing,schema,django,drf
Author: Matías Cárdenas
Author-email: cardenasmatias.1990@gmail.com
Requires-Python: >=3.7,<4.0
Classifier: Development Status :: 5 - Production/Stable
Classifier: Environment :: Web Environment
Classifier: Framework :: Django
Classifier: Framework :: Django :: 3.0
Classifier: Framework :: Django :: 3.1
Classifier: Framework :: Django :: 3.2
Classifier: Framework :: Django :: 4.0
Classifier: Framework :: Django :: 4.1
Classifier: Framework :: Pytest
Classifier: Intended Audience :: Developers
Classifier: License :: OSI Approved :: BSD License
Classifier: License :: Other/Proprietary License
Classifier: Natural Language :: English
Classifier: Operating System :: OS Independent
Classifier: Programming Language :: Python
Classifier: Programming Language :: Python :: 3
Classifier: Programming Language :: Python :: 3.7
Classifier: Programming Language :: Python :: 3.8
Classifier: Programming Language :: Python :: 3.9
Classifier: Programming Language :: Python :: 3.10
Classifier: Programming Language :: Python :: 3.11
Classifier: Programming Language :: Python :: 3.12
Classifier: Programming Language :: Python :: 3 :: Only
Classifier: Topic :: Documentation
Classifier: Topic :: Software Development
Classifier: Topic :: Software Development :: Libraries
Classifier: Topic :: Software Development :: Libraries :: Application Frameworks
Classifier: Topic :: Software Development :: Libraries :: Python Modules
Classifier: Topic :: Software Development :: Testing
Classifier: Topic :: Software Development :: Testing :: Unit
Classifier: Topic :: Utilities
Classifier: Typing :: Typed
Provides-Extra: drf-spectacular
Provides-Extra: drf-yasg
Requires-Dist: django (>=3,<4) ; python_full_version <= "3.7.0"
Requires-Dist: django (>=3,<5) ; python_version >= "3.8"
Requires-Dist: djangorestframework
Requires-Dist: drf-spectacular ; extra == "drf-spectacular"
Requires-Dist: drf-yasg ; extra == "drf-yasg"
Requires-Dist: inflection
Requires-Dist: openapi-spec-validator (>=0.4)
Requires-Dist: prance
Requires-Dist: pyYAML
Project-URL: Documentation, https://github.com/maticardenas/django-contract-tester
Project-URL: Repository, https://github.com/maticardenas/django-contract-tester
